finite_differences.py
finite_differences-0.0.0.dist-info/METADATA
finite_differences-0.0.0.dist-info/WHEEL
finite_differences-0.0.0.dist-info/top_level.txt
finite_differences-0.0.0.dist-info/RECORD
